{
  "title": "Reminder",
  "login": "Login",
  "profile": "Profile",
  "reminders": "My Reminders:",
  "loginBtn": "Login",
  "profileBtn": "Profile",

  "signin": "Sign in",
  "signup": "Sign up",
  "createUser": "Create User",
  "createAccount": "Create Account",

  "noAccount": "Don't have an account?",
  "haveAccount": "Already have an account?",
  "backLogin": "Back to login",

  "agree": "I agree to",
  "and": "and",
  "tos": "Terms of Service",
  "privacy": "Privacy Policy",

  "createReminder": "Create Reminder",

  "save": "Save",
  "cancel": "Cancel",
  "close": "Close",

  "work": "Work",
  "school":"school",
  "assignment":"Assignments",
  "toDo": "To Do",
  "important": "Important",
  "other": "Other",

  

  "logout": "You have been logged out",
  "loginRequired": "Please login first",
  "invalidCredentials": "Invalid credentials",
  "loginSuccess": "Login successful!",
  "loginError": "Invalid username or password",

  "userExists": "User already exists",
  "userRequired": "Username and password required",
  "errorUsers": "Error loading users",
  "userCreated": "User created! You can now log in.",
  "userName": "Username:",

  "account": "Account",
  "deleteAccount": "Delete account",
  "confirmDeleteAccount": "Are you sure you want to delete your account?",
  "accountDeleted": "Account deleted",
  "errorProfile": "Error loading profile",

  "usernameTooShort": "Username must be at least 3 characters long",
  "passwordTooShort": "Password must be at least 6 characters long",
  "consentRequired": "You must agree to the Terms of Service",

  "noAuthHeader": "No authorization header",
  "invalidAuthFormat": "Invalid authorization format",
  "invalidToken": "Invalid token",
  
  "noToken": "No token provided",
  "malformedToken": "Malformed token",

  "userNotFound": "User not found",
  "notAllowed": "Not allowed",
  "serverError": "Server error",

  "profileLoginRequired": "Login to see profile",

  "confirmLogout": "Are you sure you want to log out?",

  "changePassword": "Change password",
  "currentPassword": "Current password",
  "newPassword": "New password",
  "update": "Update",
  "fillBothFields": "Please fill both fields",
  "passwordUpdated": "Password updated successfully",
  "passwordUpdateFailed": "Failed to update password"


}